DeepNeuralBranchNet/__init__.py
DeepNeuralBranchNet/neuralnet.py
DeepNeuralBranchNet-0.0.14.dist-info/METADATA
DeepNeuralBranchNet-0.0.14.dist-info/WHEEL
DeepNeuralBranchNet-0.0.14.dist-info/top_level.txt
DeepNeuralBranchNet-0.0.14.dist-info/RECORD
