Metadata-Version: 2.1
Name: DeepNeuralBranchNet
Version: 0.0.14
Summary: Neural network module with branching output
Home-page: https://github.com/hamzahshabbir96/Neural-network-with-branching-output
Author: Hamzah Shabbir
Author-email: hamzahshabbir7@gmail.com
License: UNKNOWN
Keywords: Neural Network,Classification,Python,Neurons,layers
Platform: UNKNOWN
Classifier: Development Status :: 2 - Pre-Alpha
Classifier: Intended Audience :: Developers
Classifier: Operating System :: OS Independent
Classifier: Programming Language :: Python
Classifier: Programming Language :: Python :: 2
Classifier: Programming Language :: Python :: 3
Classifier: Topic :: Software Development
Classifier: Topic :: Scientific/Engineering :: Artificial Intelligence
Classifier: Topic :: Scientific/Engineering
Classifier: Topic :: Scientific/Engineering :: Artificial Life
Requires-Dist: numpy
